quantum_edward/Fitter.py
quantum_edward/Model.py
quantum_edward/NbTrolsModel.py
quantum_edward/NoNbTrolsModel.py
quantum_edward/Plotter.py
quantum_edward/TimeStep.py
quantum_edward/__init__.py
quantum_edward/utilities.py
quantum_edward-0.0.0.dist-info/LICENSE.md
quantum_edward-0.0.0.dist-info/METADATA
quantum_edward-0.0.0.dist-info/WHEEL
quantum_edward-0.0.0.dist-info/top_level.txt
quantum_edward-0.0.0.dist-info/RECORD
