Metadata-Version: 2.1
Name: quantum-edward
Version: 0.0.0
Summary: Python tools for supervised learning by Quantum Neural Networks.
Home-page: https://github.com/artiste-qb-net/Quantum_Edward
Author: Robert Tucci
Author-email: Robert.Tucci@artiste-qb.net
License: UNKNOWN
Keywords: Quantum Neural Networks
Platform: UNKNOWN
Classifier: Programming Language :: Python :: 3
Classifier: License :: OSI Approved :: MIT License
Classifier: Operating System :: OS Independent
Requires-Dist: numpy
Requires-Dist: matplotlib
Requires-Dist: scipy
